prompt_cubes/__init__.py
prompt_cubes/exceptions.py
prompt_cubes/hooks.py
prompt_cubes/loader.py
prompt_cubes/models.py
prompt_cubes/py.typed
prompt_cubes/service.py
prompt_cubes/adapters/__init__.py
prompt_cubes/adapters/anthropic.py
prompt_cubes/adapters/base.py
prompt_cubes/adapters/gemini.py
prompt_cubes/adapters/openai.py
prompt_cubes-0.1.0.dist-info/METADATA
prompt_cubes-0.1.0.dist-info/WHEEL
prompt_cubes-0.1.0.dist-info/licenses/LICENSE
prompt_cubes-0.1.0.dist-info/RECORD
