Metadata-Version: 2.4
Name: prompt-cubes
Version: 0.1.0
Summary: LEGO Constructor for LLM prompts - modular YAML-based prompt assembly with matrix configuration
Project-URL: Homepage, https://github.com/lifeaitools/prompt-cubes
Project-URL: Repository, https://github.com/lifeaitools/prompt-cubes
Project-URL: Documentation, https://github.com/lifeaitools/prompt-cubes#readme
Author-email: LifeAiTools <relishev@gmail.com>
License-Expression: Apache-2.0
License-File: LICENSE
Keywords: ai,anthropic,gemini,llm,modular,openai,prompt-engineering,prompts,templates,yaml
Classifier: Development Status :: 3 - Alpha
Classifier: Intended Audience :: Developers
Classifier: License :: OSI Approved :: Apache Software License
Classifier: Operating System :: OS Independent
Classifier: Programming Language :: Python :: 3
Classifier: Programming Language :: Python :: 3.10
Classifier: Programming Language :: Python :: 3.11
Classifier: Programming Language :: Python :: 3.12
Classifier: Topic :: Scientific/Engineering :: Artificial Intelligence
Classifier: Topic :: Software Development :: Libraries :: Python Modules
Classifier: Typing :: Typed
Requires-Python: >=3.10
Requires-Dist: pyyaml>=6.0
Provides-Extra: dev
Requires-Dist: mypy>=1.0; extra == 'dev'
Requires-Dist: pytest-cov>=4.0; extra == 'dev'
Requires-Dist: pytest>=7.0; extra == 'dev'
Requires-Dist: ruff>=0.1; extra == 'dev'
Provides-Extra: validation
Requires-Dist: pydantic>=2.0; extra == 'validation'
